ecocrop/__init__.py
ecocrop/core.py
ecocrop/model.py
ecocrop-0.2.0.dist-info/LICENSE
ecocrop-0.2.0.dist-info/METADATA
ecocrop-0.2.0.dist-info/WHEEL
ecocrop-0.2.0.dist-info/top_level.txt
ecocrop-0.2.0.dist-info/RECORD
