Metadata-Version: 2.1
Name: ecocrop
Version: 0.2.0
Summary: Ecological crop suitability model matching Recocrop (R) in Python
Home-page: https://github.com/ttwiipongwii/ecocrop
Author: Troy Wiipongwii, PhD, MPP
Author-email: ttwiipongwii@wm.edu
Classifier: Programming Language :: Python :: 3
Classifier: License :: OSI Approved :: MIT License
Classifier: Operating System :: OS Independent
Requires-Python: >=3.7
License-File: LICENSE
Requires-Dist: numpy
Requires-Dist: pandas
Requires-Dist: rasterio
Requires-Dist: matplotlib
Requires-Dist: scipy
